lightgallery.py
lightgallery-0.5.dist-info/LICENSE
lightgallery-0.5.dist-info/METADATA
lightgallery-0.5.dist-info/WHEEL
lightgallery-0.5.dist-info/top_level.txt
lightgallery-0.5.dist-info/RECORD
