Metadata-Version: 2.1
Name: lightgallery
Version: 0.5
Summary: Markdown extension to wrap images in lightbox/lightgallery
Home-page: https://github.com/g-provost/lightgallery-markdown
Author: Gauthier Provost
Author-email: gauthier@kobol.io
License: MIT License
Project-URL: Source, https://github.com/g-provost/lightgallery-markdown
Project-URL: Documentation, https://github.com/g-provost/lightgallery-markdown
Project-URL: Tracker, https://github.com/g-provost/lightgallery-markdown/issues
Platform: UNKNOWN
Classifier: Topic :: Text Processing :: Markup :: HTML
Requires-Dist: markdown (>=3.0)
